bixi/__init__.py
bixi/appcore.py
bixi/cli.py
bixi/workspace_manage.py
bixi/prediction/__init__.py
bixi/prediction/easyviz.py
bixi/prediction/to_image.py
bixi/utils/__init__.py
bixi/utils/axes_op.py
bixi/utils/collection_op.py
bixi/utils/config.py
bixi/utils/distributed.py
bixi/utils/idbg.py
bixi/utils/managed_storage.py
bixi/utils/misc.py
bixi/utils/record.py
bixi/utils/reflect.py
bixi/utils/torch_cast.py
oh_my_bixi-1.3.2.dist-info/METADATA
oh_my_bixi-1.3.2.dist-info/WHEEL
oh_my_bixi-1.3.2.dist-info/top_level.txt
oh_my_bixi-1.3.2.dist-info/RECORD
