Metadata-Version: 2.4
Name: oh-my-bixi
Version: 1.3.2
Summary: A lightweight machine learning framework and toolset for development.
Requires-Python: >=3.8
Requires-Dist: matplotlib
Requires-Dist: hydra-core>=1.1.0
Requires-Dist: numpy>=1.20
Requires-Dist: typer>=0.15
Requires-Dist: pytest>=8.0.0
Provides-Extra: dev
Requires-Dist: torch; extra == "dev"
Requires-Dist: torchvision; extra == "dev"
Requires-Dist: scipy; extra == "dev"
